fh_heroicons/__init__.py
fh_heroicons/core.py
fh_heroicons/py.typed
fh_heroicons/test_core.py
fh_heroicons-0.1.0.dist-info/METADATA
fh_heroicons-0.1.0.dist-info/WHEEL
fh_heroicons-0.1.0.dist-info/licenses/LICENSE
fh_heroicons-0.1.0.dist-info/RECORD
