Metadata-Version: 2.4
Name: fh-heroicons
Version: 0.1.0
Summary: FastHTML package for Heroicons
Project-URL: Homepage, https://github.com/vacmar01/fh-heroicons
Project-URL: Repository, https://github.com/vacmar01/fh-heroicons
Project-URL: Issues, https://github.com/vacmar01/fh-heroicons/issues
Author-email: Marius <mariusvach@gmail.com>
License-Expression: MIT
License-File: LICENSE
Keywords: fasthtml,heroicons,icons,svg
Classifier: Development Status :: 4 - Beta
Classifier: Framework :: FastAPI
Classifier: Intended Audience :: Developers
Classifier: License :: OSI Approved :: MIT License
Classifier: Programming Language :: Python :: 3
Classifier: Programming Language :: Python :: 3.10
Classifier: Programming Language :: Python :: 3.11
Classifier: Programming Language :: Python :: 3.12
Classifier: Topic :: Internet :: WWW/HTTP
Requires-Python: >=3.10
Requires-Dist: beautifulsoup4>=4.12.3
Requires-Dist: httpx>=0.27.2
Requires-Dist: lxml>=5.3.0
Requires-Dist: python-fasthtml>=0.10.1
